<annotation>
	<folder>JPEGImages</folder>
	<filename>000121.jpg</filename>
	<path>C:\Users\asus2015\Desktop\VOCdevkit\VOC2007\JPEGImages\000121.jpg</path>
	<source>
		<database>Unknown</database>
	</source>
	<size>
		<width>348</width>
		<height>280</height>
		<depth>1</depth>
	</size>
	<segmented>0</segmented>
	<object>
		<name>fiber</name>
		<pose>Unspecified</pose>
		<truncated>0</truncated>
		<difficult>0</difficult>
		<bndbox>
			<xmin>124</xmin>
			<ymin>173</ymin>
			<xmax>158</xmax>
			<ymax>204</ymax>
		</bndbox>
	</object>
</annotation>
